{
  "index": {
    "name": "react",
    "subtitle": "React",
    "tags": ["framework", "frontend"],
    "about": "A JavaScript library for building User Interfaces. Lots of people use React as the V in MVC. Since React makes no assumptions about the rest of your technology stack, it's easy to try it out on a small feature in an existing project.",
    "site": "http://facebook.github.io/react",
    "image": "react.jpg",
    "description": "Read the best free ebooks about React.",
    "books": [
      {
        "title": "The React Handbook",
        "description": "The React Handbook follows the 80/20 rule: learn in 20% of the time the 80% of a topic. I find this approach gives a well-rounded overview. This book does not try to cover everything under the sun related to React.",
        "author": "Flavio Copes",
        "pages": 220,
        "year": 2018,
        "lang": "EN",
        "added_at": "20190203",
        "url": "https://flaviocopes.com/page/ebooks/"
      },
      {
        "title": "SurviveJS React",
        "description": "Learn React while building a Kanban application. Beginner-intermediate.",
        "author": "Juho Veps채l채inen",
        "pages": 250,
        "year": 2016,
        "lang": "EN",
        "added_at": "20170219",
        "url": "https://survivejs.com/react/getting-started/"
      },
      {
        "title": "SurviveJS Webpack",
        "description": "Learn webpack while building configuration and going through its features. Beginner-intermediate.",
        "author": "Juho Veps채l채inen",
        "pages": 350,
        "year": 2016,
        "lang": "EN",
        "added_at": "20170219",
        "url": "https://survivejs.com/webpack/compared/"
      },
      {
        "title": "The Road to learn React",
        "description": "A lot of roadmaps exist on how to master React. This book uses the common sense of these roads and weaves it into the implementation of an attractive real world app. You will build a React app, which consumes the Hacker News API. On the road you will learn ES6, React with all its basics and advanced concepts and internal state management.",
        "author": "Robin Wieruch",
        "pages": 101,
        "year": 2016,
        "lang": "EN",
        "added_at": "20161214",
        "url": "https://leanpub.com/the-road-to-learn-react"
      },
      {
        "title": "React.js Succinctly",
        "description": "In React.js Succinctly, author Samer Buna introduces the novel approach to building user interfaces that React provides, and walks readers through the basics of declarative user interfaces, React components, working with user input, and more.",
        "author": "Samer Buna",
        "pages": 102,
        "year": 2016,
        "lang": "EN",
        "added_at": "20161111",
        "url": "https://www.syncfusion.com/resources/techportal/details/ebooks/Reactjs_Succinctly"
      }
    ]
  }
}
